dhlab_toolkit/__init__.py
dhlab_toolkit/constants.py
dhlab_toolkit/g2p/__init__.py
dhlab_toolkit/g2p/g2p_models.py
dhlab_toolkit/geo_data.py
dhlab_toolkit/graph_networkx_louvain.py
dhlab_toolkit/trigram_lang_model/nno_trilangmodel.json
dhlab_toolkit/trigram_lang_model/nob_trilangmodel.json
dhlab_toolkit/visualization/__init__.py
dhlab_toolkit/visualization/cloud.py
dhlab_toolkit/visualization/heatmap.py
dhlab_toolkit/wordbank/__init__.py
dhlab_toolkit/wordbank/api.py
dhlab_toolkit/wordbank/wordbank.py
dhlab_toolkit-0.3.0.dist-info/LICENSE
dhlab_toolkit-0.3.0.dist-info/METADATA
dhlab_toolkit-0.3.0.dist-info/WHEEL
dhlab_toolkit-0.3.0.dist-info/RECORD
