Metadata-Version: 2.1
Name: dhlab_toolkit
Version: 0.3.0
Summary: 
Author: Nasjonalbiblioteket 
Author-email: dhlab@nb.no
Requires-Python: >=3.10,<4.0
Classifier: Programming Language :: Python :: 3
Classifier: Programming Language :: Python :: 3.10
Classifier: Programming Language :: Python :: 3.11
Classifier: Programming Language :: Python :: 3.12
Requires-Dist: convert-pa (>=0.1.0,<0.2.0)
Requires-Dist: dhlab (>=2.32.0,<3.0.0)
Requires-Dist: google-cloud-storage (>=2.16.0,<3.0.0)
Requires-Dist: matplotlib (>=3.7.2,<4.0.0)
Requires-Dist: pandas (>=2.0.3,<3.0.0)
Requires-Dist: phonetisaurus (>=0.3.0,<0.4.0)
Requires-Dist: requests (>=2.31.0,<3.0.0)
Requires-Dist: seaborn (>=0.13.2,<0.14.0)
